optixlog/__init__.py
optixlog/client.py
optixlog/helpers.py
optixlog/query.py
optixlog/result_types.py
optixlog/types.py
optixlog/validators.py
optixlog-0.3.0.dist-info/METADATA
optixlog-0.3.0.dist-info/WHEEL
optixlog-0.3.0.dist-info/top_level.txt
optixlog-0.3.0.dist-info/RECORD
