Metadata-Version: 2.4
Name: optixlog
Version: 0.3.0
Summary: Client SDK for logging photonic simulations to OptixLog with MPI support
Author-email: OptixLog <founders@optixlog.com>
Requires-Python: >=3.8
Requires-Dist: requests
Requires-Dist: numpy
Requires-Dist: matplotlib
Requires-Dist: pillow
Requires-Dist: rich>=13.0.0
Provides-Extra: mpi
Requires-Dist: mpi4py; extra == "mpi"
Provides-Extra: meep
Requires-Dist: meep; extra == "meep"
Provides-Extra: full
Requires-Dist: mpi4py; extra == "full"
Requires-Dist: meep; extra == "full"
